{"v":"4.8.0","meta":{"g":"LottieFiles AE 1.0.0","a":"Sadjad","k":"Instagram","d":"Instagram animated icon for you designed, Enjoy!","tc":"none"},"fr":30,"ip":0,"op":43,"w":250,"h":250,"nm":"instagram_lottie","ddd":0,"assets":[],"layers":[{"ddd":0,"ind":1,"ty":4,"nm":"Shape Layer 1","parent":5,"sr":1,"ks":{"o":{"a":0,"k":100,"ix":11},"r":{"a":0,"k":0,"ix":10},"p":{"a":0,"k":[187.396,96.418,0],"ix":2},"a":{"a":0,"k":[-34.035,-58.75,0],"ix":1},"s":{"a":0,"k":[100,100,100],"ix":6}},"ao":0,"shapes":[{"ty":"gr","it":[{"ind":0,"ty":"sh","ix":1,"ks":{"a":0,"k":{"i":[[0,0],[0,0]],"o":[[0,0],[0,0]],"v":[[-34.07,-52.5],[-34,-65]],"c":false},"ix":2},"nm":"Path 1","mn":"ADBE Vector Shape - Group","hd":false},{"ty":"st","c":{"a":0,"k":[0,0,0,1],"ix":3},"o":{"a":0,"k":100,"ix":4},"w":{"a":0,"k":13,"ix":5},"lc":2,"lj":1,"ml":4,"bm":0,"nm":"Stroke 1","mn":"ADBE Vector Graphic - Stroke","hd":false},{"ty":"tr","p":{"a":0,"k":[0,0],"ix":2},"a":{"a":0,"k":[0,0],"ix":1},"s":{"a":0,"k":[100,100],"ix":3},"r":{"a":0,"k":0,"ix":6},"o":{"a":0,"k":100,"ix":7},"sk":{"a":0,"k":0,"ix":4},"sa":{"a":0,"k":0,"ix":5},"nm":"Transform"}],"nm":"Shape 1","np":3,"cix":2,"bm":0,"ix":1,"mn":"ADBE Vector Group","hd":false}],"ip":13,"op":21,"st":0,"bm":0},{"ddd":0,"ind":2,"ty":3,"nm":"Null 1","sr":1,"ks":{"o":{"a":0,"k":0,"ix":11},"r":{"a":1,"k":[{"i":{"x":[0.3],"y":[1]},"o":{"x":[0.7],"y":[0]},"t":6,"s":[0]},{"i":{"x":[0.3],"y":[1]},"o":{"x":[0.7],"y":[0]},"t":13,"s":[-90]},{"i":{"x":[0.3],"y":[1]},"o":{"x":[0.7],"y":[0]},"t":28,"s":[-90]},{"t":36,"s":[0]}],"ix":10},"p":{"a":1,"k":[{"i":{"x":0.3,"y":1},"o":{"x":0.7,"y":0},"t":6,"s":[125,125,0],"to":[0,-3.833,0],"ti":[0,3.833,0]},{"i":{"x":0.3,"y":0.3},"o":{"x":0.7,"y":0.7},"t":13,"s":[125,102,0],"to":[0,0,0],"ti":[0,0,0]},{"i":{"x":0.3,"y":1},"o":{"x":0.7,"y":0},"t":20,"s":[125,102,0],"to":[0,5.667,0],"ti":[0,-3.833,0]},{"i":{"x":0.3,"y":1},"o":{"x":0.7,"y":0},"t":28,"s":[125,136,0],"to":[0,3.833,0],"ti":[0,1.833,0]},{"t":36,"s":[125,125,0]}],"ix":2},"a":{"a":0,"k":[0,0,0],"ix":1},"s":{"a":0,"k":[100,100,100],"ix":6}},"ao":0,"ip":0,"op":241,"st":0,"bm":0},{"ddd":0,"ind":3,"ty":4,"nm":"point","parent":2,"sr":1,"ks":{"o":{"a":1,"k":[{"i":{"x":[0.3],"y":[1]},"o":{"x":[0.7],"y":[0]},"t":6,"s":[100]},{"i":{"x":[0.3],"y":[1]},"o":{"x":[0.7],"y":[0]},"t":13,"s":[0]},{"i":{"x":[0.3],"y":[1]},"o":{"x":[0.7],"y":[0]},"t":20,"s":[100]},{"i":{"x":[0.3],"y":[1]},"o":{"x":[0.7],"y":[0]},"t":28,"s":[100]},{"t":36,"s":[100]}],"ix":11},"r":{"a":0,"k":0,"ix":10},"p":{"a":1,"k":[{"i":{"x":0.3,"y":1},"o":{"x":0.7,"y":0},"t":6,"s":[45.875,-45.833,0],"to":[-4,0,0],"ti":[4,0,0]},{"i":{"x":0.3,"y":0.3},"o":{"x":0.7,"y":0.7},"t":13,"s":[21.875,-45.833,0],"to":[0,0,0],"ti":[0,0,0]},{"i":{"x":0.3,"y":1},"o":{"x":0.7,"y":0},"t":20,"s":[21.875,-45.833,0],"to":[5.667,0,0],"ti":[-4,0,0]},{"i":{"x":0.3,"y":1},"o":{"x":0.7,"y":0},"t":28,"s":[55.875,-45.833,0],"to":[4,0,0],"ti":[1.667,0,0]},{"t":36,"s":[45.875,-45.833,0]}],"ix":2},"a":{"a":0,"k":[6.542,6.5,0],"ix":1},"s":{"a":0,"k":[130,130,100],"ix":6}},"ao":0,"shapes":[{"ty":"gr","it":[{"ind":0,"ty":"sh","ix":1,"ks":{"a":0,"k":{"i":[[0,0],[0,0]],"o":[[0,0],[0,0]],"v":[[6.5,6.5],[6.584,6.5]],"c":false},"ix":2},"nm":"Path 1","mn":"ADBE Vector Shape - Group","hd":false},{"ty":"st","c":{"a":0,"k":[0,0,0,1],"ix":3},"o":{"a":0,"k":100,"ix":4},"w":{"a":0,"k":13,"ix":5},"lc":2,"lj":2,"bm":0,"nm":"Stroke 1","mn":"ADBE Vector Graphic - Stroke","hd":false},{"ty":"tr","p":{"a":0,"k":[0,0],"ix":2},"a":{"a":0,"k":[0,0],"ix":1},"s":{"a":0,"k":[100,100],"ix":3},"r":{"a":0,"k":0,"ix":6},"o":{"a":0,"k":100,"ix":7},"sk":{"a":0,"k":0,"ix":4},"sa":{"a":0,"k":0,"ix":5},"nm":"Transform"}],"nm":"Group 1","np":2,"cix":2,"bm":0,"ix":1,"mn":"ADBE Vector Group","hd":false}],"ip":0,"op":241,"st":0,"bm":0},{"ddd":0,"ind":4,"ty":4,"nm":"center","parent":2,"sr":1,"ks":{"o":{"a":0,"k":100,"ix":11},"r":{"a":0,"k":0,"ix":10},"p":{"a":1,"k":[{"i":{"x":0.3,"y":1},"o":{"x":0.7,"y":0},"t":6,"s":[0.36,0.75,0],"to":[-4.667,0,0],"ti":[4.667,0,0]},{"i":{"x":0.3,"y":0.3},"o":{"x":0.7,"y":0.7},"t":13,"s":[-27.64,0.75,0],"to":[0,0,0],"ti":[0,0,0]},{"i":{"x":0.3,"y":1},"o":{"x":0.7,"y":0},"t":20,"s":[-27.64,0.75,0],"to":[9.333,0,0],"ti":[-4.667,0,0]},{"i":{"x":0.3,"y":1},"o":{"x":0.7,"y":0},"t":28,"s":[28.36,0.75,0],"to":[4.667,0,0],"ti":[4.667,0,0]},{"t":36,"s":[0.36,0.75,0]}],"ix":2},"a":{"a":0,"k":[89.841,88.731,0],"ix":1},"s":{"a":1,"k":[{"i":{"x":[0.3,0.3,0.3],"y":[1,1,1]},"o":{"x":[0.7,0.7,0.7],"y":[0,0,0]},"t":6,"s":[100,100,100]},{"i":{"x":[0.3,0.3,0.3],"y":[1,1,1]},"o":{"x":[0.7,0.7,0.7],"y":[0,0,0]},"t":28,"s":[100,100,100]},{"t":36,"s":[100,100,100]}],"ix":6}},"ao":0,"shapes":[{"ty":"gr","it":[{"ind":0,"ty":"sh","ix":1,"ks":{"a":0,"k":{"i":[[-2.153,-14.525],[18.21,-2.7],[2.7,18.21],[-18.21,2.7],[-3.242,-0.481]],"o":[[2.701,18.21],[-18.21,2.701],[-2.701,-18.211],[3.242,-0.481],[14.524,2.153]],"v":[[32.973,-5.999],[4.889,31.863],[-32.973,3.78],[-4.889,-34.083],[4.889,-34.083]],"c":true},"ix":2},"nm":"Path 1","mn":"ADBE Vector Shape - Group","hd":false},{"ty":"st","c":{"a":0,"k":[0,0,0,1],"ix":3},"o":{"a":0,"k":100,"ix":4},"w":{"a":1,"k":[{"i":{"x":[0.3],"y":[1]},"o":{"x":[0.7],"y":[0]},"t":6,"s":[13]},{"i":{"x":[0.3],"y":[1]},"o":{"x":[0.7],"y":[0]},"t":13,"s":[15]},{"i":{"x":[0.3],"y":[1]},"o":{"x":[0.7],"y":[0]},"t":20,"s":[15]},{"i":{"x":[0.3],"y":[1]},"o":{"x":[0.7],"y":[0]},"t":28,"s":[15]},{"t":36,"s":[13]}],"ix":5},"lc":2,"lj":2,"bm":0,"nm":"Stroke 1","mn":"ADBE Vector Graphic - Stroke","hd":false},{"ty":"tr","p":{"a":0,"k":[89.841,88.731],"ix":2},"a":{"a":0,"k":[0,0],"ix":1},"s":{"a":0,"k":[100,100],"ix":3},"r":{"a":0,"k":0,"ix":6},"o":{"a":0,"k":100,"ix":7},"sk":{"a":0,"k":0,"ix":4},"sa":{"a":0,"k":0,"ix":5},"nm":"Transform"}],"nm":"Group 1","np":2,"cix":2,"bm":0,"ix":1,"mn":"ADBE Vector Group","hd":false}],"ip":0,"op":241,"st":0,"bm":0},{"ddd":0,"ind":5,"ty":4,"nm":"frame","parent":2,"sr":1,"ks":{"o":{"a":0,"k":100,"ix":11},"r":{"a":0,"k":0,"ix":10},"p":{"a":0,"k":[0,0,0],"ix":2},"a":{"a":0,"k":[137.501,137.501,0],"ix":1},"s":{"a":0,"k":[100,100,100],"ix":6}},"ao":0,"shapes":[{"ty":"gr","it":[{"ind":0,"ty":"sh","ix":1,"ks":{"a":1,"k":[{"i":{"x":0.3,"y":1},"o":{"x":0.7,"y":0},"t":6,"s":[{"i":[[-23.012,0],[0,0],[0,-23.012],[0,0],[23.012,0],[0,0],[0,0],[0,23.012],[0,0],[0,0]],"o":[[0,0],[23.012,0],[0,0],[0,23.012],[0,0],[0,0],[-23.012,0],[0,0],[0,0],[0,-23.012]],"v":[[-41.667,-83.333],[41.667,-83.333],[83.333,-41.666],[83.333,41.667],[41.667,83.334],[-1.245,83.334],[-41.667,83.334],[-83.333,41.667],[-83.333,3.018],[-83.333,-41.666]],"c":true}]},{"i":{"x":0.3,"y":1},"o":{"x":0.7,"y":0},"t":13,"s":[{"i":[[-23.012,0],[0,0],[0,-23.012],[0,0],[23.012,0],[0,0],[0,0],[0,23.012],[0,0],[0,0]],"o":[[0,0],[23.012,0],[0,0],[0,23.012],[0,0],[0,0],[-23.012,0],[0,0],[0,0],[0,-23.012]],"v":[[-55.834,-94.837],[1.499,-93.838],[43.166,-52.171],[42.851,58.162],[1.184,99.829],[-12.464,99.329],[-56.149,98.83],[-97.816,57.163],[-97.666,4.663],[-97.501,-53.17]],"c":true}]},{"i":{"x":0.3,"y":1},"o":{"x":0.7,"y":0},"t":20,"s":[{"i":[[-23.012,0],[0,0],[0,-23.012],[0,0],[23.012,0],[0,0],[0,0],[0,23.012],[0,0],[0,0]],"o":[[0,0],[23.012,0],[0,0],[0,23.012],[0,0],[0,0],[-23.012,0],[0,0],[0,0],[0,-23.012]],"v":[[-55.834,-94.837],[1.499,-93.838],[43.166,-52.171],[42.851,58.162],[1.184,99.829],[-12.464,99.329],[-56.149,98.83],[-97.816,57.163],[-97.666,4.663],[-97.501,-53.17]],"c":true}]},{"i":{"x":0.3,"y":1},"o":{"x":0.7,"y":0},"t":28,"s":[{"i":[[-23.012,0],[0,0],[0,-23.012],[0,0],[23.012,0],[0,0],[0,0],[0,23.012],[0,0],[0,0]],"o":[[0,0],[23.012,0],[0,0],[0,23.012],[0,0],[0,0],[-23.012,0],[0,0],[0,0],[0,-23.012]],"v":[[-14.667,-83.003],[39.667,-82.838],[81.333,-41.171],[81.333,42.162],[39.667,83.829],[11.688,83.744],[-14.667,83.664],[-56.333,41.997],[-56.333,3.348],[-56.333,-41.336]],"c":true}]},{"t":36,"s":[{"i":[[-23.012,0],[0,0],[0,-23.012],[0,0],[23.012,0],[0,0],[0,0],[0,23.012],[0,0],[0,0]],"o":[[0,0],[23.012,0],[0,0],[0,23.012],[0,0],[0,0],[-23.012,0],[0,0],[0,0],[0,-23.012]],"v":[[-41.667,-83.333],[41.667,-83.333],[83.333,-41.666],[83.333,41.667],[41.667,83.334],[-1.245,83.334],[-41.667,83.334],[-83.333,41.667],[-83.333,3.018],[-83.333,-41.666]],"c":true}]}],"ix":2},"nm":"Path 1","mn":"ADBE Vector Shape - Group","hd":false},{"ty":"st","c":{"a":0,"k":[0,0,0,1],"ix":3},"o":{"a":0,"k":100,"ix":4},"w":{"a":0,"k":13,"ix":5},"lc":2,"lj":2,"bm":0,"nm":"Stroke 1","mn":"ADBE Vector Graphic - Stroke","hd":false},{"ty":"tr","p":{"a":0,"k":[137.501,137.501],"ix":2},"a":{"a":0,"k":[0,0],"ix":1},"s":{"a":0,"k":[100,100],"ix":3},"r":{"a":0,"k":0,"ix":6},"o":{"a":0,"k":100,"ix":7},"sk":{"a":0,"k":0,"ix":4},"sa":{"a":0,"k":0,"ix":5},"nm":"Transform"}],"nm":"Group 1","np":2,"cix":2,"bm":0,"ix":1,"mn":"ADBE Vector Group","hd":false}],"ip":0,"op":241,"st":0,"bm":0}],"markers":[]}